rewar/__init__.py
rewar/main.py
rewar-1.0.0.dist-info/METADATA
rewar-1.0.0.dist-info/WHEEL
rewar-1.0.0.dist-info/top_level.txt
rewar-1.0.0.dist-info/RECORD
